setup.py
twoost/__init__.py
twoost/_geninit_worker_tac.py
twoost/_misc.py
twoost/amqp.py
twoost/app.py
twoost/authhmac.py
twoost/conf.py
twoost/cron.py
twoost/dbpool.py
twoost/dbshell.py
twoost/dbtools.py
twoost/default_settings.py
twoost/email.py
twoost/geninit.py
twoost/health.py
twoost/httprpc.py
twoost/log.py
twoost/manhole.py
twoost/memcache.py
twoost/pclient.py
twoost/rpcproxy.py
twoost/timed.py
twoost/web.py
twoost.egg-info/PKG-INFO
twoost.egg-info/SOURCES.txt
twoost.egg-info/dependency_links.txt
twoost.egg-info/requires.txt
twoost.egg-info/top_level.txt