Metadata-Version: 1.1
Name: twoost
Version: 0.3.3.1
Summary: Twoost is a collection of tools and helpers for the Twisted framework.
Home-page: UNKNOWN
Author: Andrei Zhlobich
Author-email: a.zhlobich@gmail.com
License: UNKNOWN
Platform: Independant
Classifier: Development Status :: 4 - Beta
Classifier: Framework :: Twisted
Classifier: Intended Audience :: Developers
Classifier: License :: OSI Approved :: MIT License
Classifier: Natural Language :: English
Classifier: Operating System :: OS Independent
Classifier: Topic :: Software Development :: Libraries :: Python Modules
